AUTHORS.rst
HISTORY.rst
LICENSE
MANIFEST.in
README.rst
setup.cfg
setup.py
tests/__init__.py
tests/test_varint.py
wspr_varint/__init__.py
wspr_varint/varint.py
wspr_varint.egg-info/PKG-INFO
wspr_varint.egg-info/SOURCES.txt
wspr_varint.egg-info/dependency_links.txt
wspr_varint.egg-info/not-zip-safe
wspr_varint.egg-info/top_level.txt