Metadata-Version: 1.2
Name: wspr-varint
Version: 1.1.1
Summary: A variable length integer implementation for the wspr project.
Home-page: UNKNOWN
Author: Arkadiusz Michał Ryś
Author-email: Arkadiusz.Michal.Rys@gmail.com
License: MIT license
Keywords: wspr_varint
Platform: UNKNOWN
Classifier: Intended Audience :: Developers
Classifier: License :: OSI Approved :: MIT License
Classifier: Natural Language :: English
Classifier: Programming Language :: Python :: 3.8
Requires-Python: >=3.8, <4
